scpy4reactome/AutoencoderNetwork.py
scpy4reactome/GeneRelEval.py
scpy4reactome/ScJSONServer.py
scpy4reactome/ScanpyWrapper.py
scpy4reactome/__init__.py
scpy4reactome/__main__.py
scpy4reactome-0.1.0.dist-info/METADATA
scpy4reactome-0.1.0.dist-info/WHEEL
scpy4reactome-0.1.0.dist-info/top_level.txt
scpy4reactome-0.1.0.dist-info/RECORD
